mgi_alphatool/__init__.py
mgi_alphatool/cli.py
mgi_alphatool/context.py
mgi_alphatool/liquid.py
mgi_alphatool/app/commands/__init__.py
mgi_alphatool/app/commands/base.py
mgi_alphatool/app/commands/command.py
mgi_alphatool/app/commands/heatershaker.py
mgi_alphatool/app/commands/labware.py
mgi_alphatool/app/commands/liquid_handling.py
mgi_alphatool/app/commands/magnetic.py
mgi_alphatool/app/commands/pause.py
mgi_alphatool/app/commands/temperature.py
mgi_alphatool/app/commands/thermocycler.py
mgi_alphatool/app/handle/__init__.py
mgi_alphatool/commands/__init__.py
mgi_alphatool/commands/command.py
mgi_alphatool/commands/labware.py
mgi_alphatool/commands/liquid.py
mgi_alphatool/commands/mark.py
mgi_alphatool/commands/module.py
mgi_alphatool/commands/pipette.py
mgi_alphatool/commands/wait.py
mgi_alphatool/data/labware/biorad_96_wellplate_200l.json
mgi_alphatool/data/labware/biorad_96_wellplate_200ul.json
mgi_alphatool/data/labware/biorad_96_wellplate_200ul_pcr copy.json
mgi_alphatool/data/labware/biorad_96_wellplate_200ul_pcr.json
mgi_alphatool/data/labware/corning_96_wellplate_200ul_pcr copy.json
mgi_alphatool/data/labware/corning_96_wellplate_200ul_pcr.json
mgi_alphatool/data/labware/corning_96_wellplate_360l.json
mgi_alphatool/data/labware/corning_96_wellplate_360ul.json
mgi_alphatool/data/labware/corning_96_wellplate_360ul_flat.json
mgi_alphatool/data/labware/gsbio_96_wellplate_100ul.json
mgi_alphatool/data/labware/gsbio_96_wellplate_200ul.json
mgi_alphatool/data/labware/mdk_24_aluminumBlock_24x1.5ml_screwcap copy.json
mgi_alphatool/data/labware/mdk_24_aluminumBlock_24x1.5ml_screwcap.json
mgi_alphatool/data/labware/mdk_24_aluminumBlock_24x2ml_snapcap copy.json
mgi_alphatool/data/labware/mdk_24_aluminumBlock_24x2ml_snapcap.json
mgi_alphatool/data/labware/mdk_24_aluminumBlock_24x5ml.json
mgi_alphatool/data/labware/mdk_24_aluminumblock_5ml copy.json
mgi_alphatool/data/labware/mdk_24_aluminumblock_5ml.json
mgi_alphatool-1.4.7.dist-info/LICENSE
mgi_alphatool-1.4.7.dist-info/METADATA
mgi_alphatool-1.4.7.dist-info/WHEEL
mgi_alphatool-1.4.7.dist-info/entry_points.txt
mgi_alphatool-1.4.7.dist-info/top_level.txt
mgi_alphatool-1.4.7.dist-info/RECORD
