Metadata-Version: 2.1
Name: mgi_alphatool
Version: 1.4.7
Summary: Library for designing protocols and running on MGI liquid handling machines.
Author: Brian Chan
Author-email: chanwingho@mgi-tech.com
Maintainer: Brian Chan
Maintainer-email: chanwingho@mgi-tech.com
Keywords: pipette,lab,automation,liquid handler,pcr,protocols,workstation,mgi
Classifier: Development Status :: 4 - Beta
Classifier: Programming Language :: Python :: 3
Classifier: License :: OSI Approved :: Apache Software License
Classifier: Operating System :: OS Independent
Classifier: Topic :: Scientific/Engineering
Classifier: Intended Audience :: Science/Research
Requires-Python: >=3.8
License-File: LICENSE
Requires-Dist: pydantic (>=2.7.1)
Requires-Dist: requests (>=2.32.3)
